MANIFEST.in
README.md
setup.py
v2t/__init__.py
v2t/__version__.py
v2t/cli.py
v2t/exceptions.py
v2t/help.py
v2t/models.py
v2t/playground.py
v2t/status_codes.py
v2t/utils.py
v2t.egg-info/PKG-INFO
v2t.egg-info/SOURCES.txt
v2t.egg-info/dependency_links.txt
v2t.egg-info/entry_points.txt
v2t.egg-info/not-zip-safe
v2t.egg-info/requires.txt
v2t.egg-info/top_level.txt