Metadata-Version: 2.1
Name: v2t
Version: 1.1.5
Summary: AzatAI Video To Text Converter. 
Home-page: https://github.com/AzatAI/v2t
Author: Yaakov Azat
Author-email: yaakovazat@gmail.com
License: MIT
Project-URL: Documentation, https://azat.ai
Project-URL: Source, https://github.com/AzatAI/v2t
Platform: UNKNOWN
Classifier: Development Status :: 5 - Production/Stable
Classifier: Intended Audience :: Developers
Classifier: Natural Language :: English
Classifier: Programming Language :: Python
Classifier: Programming Language :: Python :: 3
Classifier: Programming Language :: Python :: 3.5
Classifier: Programming Language :: Python :: 3.6
Classifier: Programming Language :: Python :: 3.7
Classifier: Programming Language :: Python :: 3.8
Classifier: Programming Language :: Python :: Implementation :: CPython
Classifier: Programming Language :: Python :: Implementation :: PyPy
Requires-Python: >=3.5
